test_verdict.py
verdict.py
verdict-1.2.dist-info/LICENSE
verdict-1.2.dist-info/METADATA
verdict-1.2.dist-info/WHEEL
verdict-1.2.dist-info/top_level.txt
verdict-1.2.dist-info/RECORD
