Metadata-Version: 2.1
Name: verdict
Version: 1.2
Summary: A class for flexible manipulation of nested data.
Home-page: https://github.com/zhafen/verdict
Author: Zach Hafen
Author-email: zachary.h.hafen@gmail.com
Classifier: Programming Language :: Python :: 3
Classifier: License :: OSI Approved :: MIT License
Classifier: Operating System :: OS Independent
License-File: LICENSE
Requires-Dist: h5py (>=3.7.0)
Requires-Dist: h5sparse (>=0.1.0)
Requires-Dist: mock (>=4.0.3)
Requires-Dist: numpy (>=1.23.5)
Requires-Dist: pandas (>=1.5.2)
Requires-Dist: scipy (>=1.9.3)
Requires-Dist: setuptools (>=65.6.3)
Requires-Dist: six (>=1.16.0)
Requires-Dist: tqdm (>=4.64.1)
